[
	{
		"name": "common",
		"blocks": [
			{
				"name": "Carousel",
				"directory": "src/common/Carousel",
				"category": "common",
				"tests": false,
				"subdirectory": true,
				"list": true,
				"files": [
					"CarouselContent.tsx",
					"CarouselItem.tsx",
					"CarouselNext.tsx",
					"CarouselPrevious.tsx",
					"CarouselRoot.tsx",
					"context.ts",
					"hooks",
					"index.tsx",
					"types.ts"
				],
				"localDependencies": [
					"utils/cn"
				],
				"dependencies": [
					"react@^18.3.1",
					"@equinor/eds-core-react@^0.42.5",
					"@equinor/eds-icons",
					"embla-carousel-react@^8.5.1"
				],
				"devDependencies": [],
				"_imports_": {
					"../../utils/cn": "{{utils/cn}}"
				}
			},
			{
				"name": "Command",
				"directory": "src/common/Command",
				"category": "common",
				"tests": false,
				"subdirectory": true,
				"list": true,
				"files": [
					"CommandEmpty.tsx",
					"CommandGroup.tsx",
					"CommandInput.tsx",
					"CommandItem.tsx",
					"CommandList.tsx",
					"CommandRoot.tsx",
					"CommandSeparator.tsx",
					"CommandShortcut.tsx",
					"index.tsx"
				],
				"localDependencies": [
					"utils/cn",
					"common/ScrollArea"
				],
				"dependencies": [
					"cmdk@^1.0.4",
					"react@^18.3.1",
					"@equinor/eds-core-react@^0.42.5",
					"@equinor/eds-icons"
				],
				"devDependencies": [],
				"_imports_": {
					"../../utils/cn": "{{utils/cn}}",
					"../ScrollArea": "{{common/ScrollArea}}"
				}
			},
			{
				"name": "Dialog",
				"directory": "src/common/Dialog",
				"category": "common",
				"tests": false,
				"subdirectory": true,
				"list": true,
				"files": [
					"index.tsx"
				],
				"localDependencies": [
					"utils/cn"
				],
				"dependencies": [
					"react@^18.3.1",
					"@radix-ui/react-dialog@^1.1.2"
				],
				"devDependencies": [],
				"_imports_": {
					"../../utils/cn": "{{utils/cn}}"
				}
			},
			{
				"name": "ScrollArea",
				"directory": "src/common/ScrollArea",
				"category": "common",
				"tests": false,
				"subdirectory": true,
				"list": true,
				"files": [
					"index.tsx"
				],
				"localDependencies": [
					"utils/cn"
				],
				"dependencies": [
					"react@^18.3.1",
					"@radix-ui/react-scroll-area@^1.2.1"
				],
				"devDependencies": [],
				"_imports_": {
					"../../utils/cn": "{{utils/cn}}"
				}
			}
		]
	},
	{
		"name": "config",
		"blocks": [
			{
				"name": "tailwind.config",
				"directory": "src/config",
				"category": "config",
				"tests": false,
				"subdirectory": false,
				"list": true,
				"files": [
					"tailwind.config.ts"
				],
				"localDependencies": [],
				"_imports_": {},
				"dependencies": [],
				"devDependencies": [
					"tailwindcss@^3.4.16"
				]
			},
			{
				"name": "vite.config",
				"directory": "src/config",
				"category": "config",
				"tests": false,
				"subdirectory": false,
				"list": true,
				"files": [
					"vite.config.ts"
				],
				"localDependencies": [],
				"_imports_": {},
				"dependencies": [],
				"devDependencies": [
					"@vitejs/plugin-react@^4.3.4",
					"vite@^6.0.3",
					"vite-plugin-checker@^0.8.0"
				]
			}
		]
	},
	{
		"name": "utils",
		"blocks": [
			{
				"name": "cn",
				"directory": "src/utils",
				"category": "utils",
				"tests": false,
				"subdirectory": false,
				"list": true,
				"files": [
					"cn.ts"
				],
				"localDependencies": [],
				"_imports_": {},
				"dependencies": [
					"clsx@^2.1.1",
					"tailwind-merge@^2.5.5"
				],
				"devDependencies": []
			}
		]
	}
]